SimpleSteem-1.1.18.dist-info/DESCRIPTION.rst
SimpleSteem-1.1.18.dist-info/METADATA
SimpleSteem-1.1.18.dist-info/RECORD
SimpleSteem-1.1.18.dist-info/WHEEL
SimpleSteem-1.1.18.dist-info/metadata.json
SimpleSteem-1.1.18.dist-info/top_level.txt
simplesteem/__init__.py
simplesteem/config.py
simplesteem/default.py
simplesteem/makeconfig.py
simplesteem/simplesteem.py
simplesteem/steemconnectutil.py
simplesteem/util.py
