Metadata-Version: 2.0
Name: SimpleSteem
Version: 1.1.18
Summary: UNKNOWN
Home-page: http://github.com/artolabs/simplesteem
Author: ArtoLabs
Author-email: artopium@gmail.com
License: MIT
Keywords: steem steemit steem-python python3
Platform: UNKNOWN
Requires-Dist: python-dateutil
Requires-Dist: screenlogger (==1.3.1)
Requires-Dist: steem (==1.0.0)
Requires-Dist: steemconnect (==0.0.2)
Requires-Dist: urllib3 (==1.24.2)
